operondemmo
