Metadata-Version: 1.0
Name: operondemmo
Version: 0.0.15
Summary: an independent demo of KNOWN operon predict method
Home-page: https://github.com/GodInLove/operondemmo
Author: yaodongliu
Author-email: yd.liu.scu@gmail.com
License: GPLv3
Keywords: operon
Platform: UNKNOWN
